ducoapi.py
ducoapi-0.0.2.dist-info/LICENSE.txt
ducoapi-0.0.2.dist-info/METADATA
ducoapi-0.0.2.dist-info/WHEEL
ducoapi-0.0.2.dist-info/top_level.txt
ducoapi-0.0.2.dist-info/RECORD
