Metadata-Version: 2.1
Name: ducoapi
Version: 0.0.2
Summary: Duino-Coin Mining library for Python.
Home-page: UNKNOWN
Author: Alicia426
Author-email: alicia426@protonmail.com
License: UNKNOWN
Platform: UNKNOWN
Classifier: Programming Language :: Python :: 3
Classifier: License :: OSI Approved :: MIT License
Classifier: Operating System :: OS Independent
Requires-Python: >=3.6
